Workbook

Sheet Read Me
A1: ShopEase QA Workbook
A2: SIMULATED PROJECT: ShopEase is a fictional application. Nothing in this workbook has been executed yet. Every test case starts as Not Executed.
A4: Sheets
A5: Summary – counts and percentages calculated by formulas. They show Not started until you execute tests.
A6: Test Cases – all 67 manual test cases. Status and Actual Result are read from the Execution Tracker (do not type in them).
A7: Execution Tracker – the ONLY place where you record results. Yellow cells are for you to fill in.
A8: Defect Tracker – 10 SAMPLE defects (Type = SAMPLE, for learning). Add your real defects in the yellow rows below them with Type = ACTUAL.
A9: RTM – requirement to test case to SQL query to expected database state. Execution Status is read from the Execution Tracker.
A11: How to record a result (example of the format; this is NOT a real result)
A12: In Execution Tracker pick Status from the drop-down (Pass / Fail / Blocked / Not Executed), type your name, the date (for example 2026-11-02), what you actually saw, and the Defect ID if the test failed (for example BUG-001).
A13: Example row: TC_REG_02 | Fail | Rishi | 2026-11-02 | System accepted the duplicate email and created a second account | BUG-001
A15: Legend
... A17: SQL query IDs (Q01 to Q48) are in sql/03_validation_queries.sql and explained in docs/sql_query_guide.md.

Sheet Summary
A1: Test Execution Summary
A2: All values are formulas on the Execution Tracker. They show Not started until you execute tests.
A4: Total test cases | B4: =COUNTA('Execution Tracker'!A2:A68) -> 67
A5: Pass | B5: =COUNTIF('Execution Tracker'!D2:D68,"Pass") -> 0
A6: Fail | B6: =COUNTIF('Execution Tracker'!D2:D68,"Fail") -> 0
A7: Blocked | B7: =COUNTIF('Execution Tracker'!D2:D68,"Blocked") -> 0
A8: Not Executed | B8: =COUNTIF('Execution Tracker'!D2:D68,"Not Executed") -> 67
A9: Executed (Pass + Fail + Blocked) | B9: =B5+B6+B7 -> 0
A10: Pass % of executed | B10: =IF(B9=0,"Not started",B5/B9) -> Not started
A11: Execution progress % (executed / total) | B11: =IF(B4=0,"n/a",B9/B4) -> 0
A12: Check: counts add up to total | B12: =IF(B5+B6+B7+B8=B4,"OK","CHECK STATUS VALUES") -> OK
A14: Results by module
A15: Module | B15: Total | C15: Pass | D15: Fail | E15: Blocked | F15: Not Executed
A16: User Registration | B16: =COUNTIF('Execution Tracker'!$B$2:$B$68,A16) -> 9 | C16: =COUNTIFS('Execution Tracker'!$B$2:$B$68,$A16,'Execution Tracker'!$D$2:$D$68,"Pass") -> 0 | D16: =COUNTIFS('Execution Tracker'!$B$2:$B$68,$A16,'Execution Tracker'!$D$2:$D$68,"Fail") -> 0 | E16: =COUNTIFS('Execution Tracker'!$B$2:$B$68,$A16,'Execution Tracker'!$D$2:$D$68,"Blocked") -> 0 | F16: =COUNTIFS('Execution Tracker'!$B$2:$B$68,$A16,'Execution Tracker'!$D$2:$D$68,"Not Executed") -> 9
A17: Login and Logout | B17: =COUNTIF('Execution Tracker'!$B$2:$B$68,A17) -> 7 | C17: =COUNTIFS('Execution Tracker'!$B$2:$B$68,$A17,'Execution Tracker'!$D$2:$D$68,"Pass") -> 0 | D17: =COUNTIFS('Execution Tracker'!$B$2:$B$68,$A17,'Execution Tracker'!$D$2:$D$68,"Fail") -> 0 | E17: =COUNTIFS('Execution Tracker'!$B$2:$B$68,$A17,'Execution Tracker'!$D$2:$D$68,"Blocked") -> 0 | F17: =COUNTIFS('Execution Tracker'!$B$2:$B$68,$A17,'Execution Tracker'!$D$2:$D$68,"Not Executed") -> 7
A18: Product Search | B18: =COUNTIF('Execution Tracker'!$B$2:$B$68,A18) -> 4 | C18: =COUNTIFS('Execution Tracker'!$B$2:$B$68,$A18,'Execution Tracker'!$D$2:$D$68,"Pass") -> 0 | D18: =COUNTIFS('Execution Tracker'!$B$2:$B$68,$A18,'Execution Tracker'!$D$2:$D$68,"Fail") -> 0 | E18: =COUNTIFS('Execution Tracker'!$B$2:$B$68,$A18,'Execution Tracker'!$D$2:$D$68,"Blocked") -> 0 | F18: =COUNTIFS('Execution Tracker'!$B$2:$B$68,$A18,'Execution Tracker'!$D$2:$D$68,"Not Executed") -> 4
A19: Categories and Product Details | B19: =COUNTIF('Execution Tracker'!$B$2:$B$68,A19) -> 4 | C19: =COUNTIFS('Execution Tracker'!$B$2:$B$68,$A19,'Execution Tracker'!$D$2:$D$68,"Pass") -> 0 | D19: =COUNTIFS('Execution Tracker'!$B$2:$B$68,$A19,'Execution Tracker'!$D$2:$D$68,"Fail") -> 0 | E19: =COUNTIFS('Execution Tracker'!$B$2:$B$68,$A19,'Execution Tracker'!$D$2:$D$68,"Blocked") -> 0 | F19: =COUNTIFS('Execution Tracker'!$B$2:$B$68,$A19,'Execution Tracker'!$D$2:$D$68,"Not Executed") -> 4
A20: Shopping Cart | B20: =COUNTIF('Execution Tracker'!$B$2:$B$68,A20) -> 5 | C20: =COUNTIFS('Execution Tracker'!$B$2:$B$68,$A20,'Execution Tracker'!$D$2:$D$68,"Pass") -> 0 | D20: =COUNTIFS('Execution Tracker'!$B$2:$B$68,$A20,'Execution Tracker'!$D$2:$D$68,"Fail") -> 0 | E20: =COUNTIFS('Execution Tracker'!$B$2:$B$68,$A20,'Execution Tracker'!$D$2:$D$68,"Blocked") -> 0 | F20: =COUNTIFS('Execution Tracker'!$B$2:$B$68,$A20,'Execution Tracker'!$D$2:$D$68,"Not Executed") -> 5
A21: Quantity Updates | B21: =COUNTIF('Execution Tracker'!$B$2:$B$68,A21) -> 5 | C21: =COUNTIFS('Execution Tracker'!$B$2:$B$68,$A21,'Execution Tracker'!$D$2:$D$68,"Pass") -> 0 | D21: =COUNTIFS('Execution Tracker'!$B$2:$B$68,$A21,'Execution Tracker'!$D$2:$D$68,"Fail") -> 0 | E21: =COUNTIFS('Execution Tracker'!$B$2:$B$68,$A21,'Execution Tracker'!$D$2:$D$68,"Blocked") -> 0 | F21: =COUNTIFS('Execution Tracker'!$B$2:$B$68,$A21,'Execution Tracker'!$D$2:$D$68,"Not Executed") -> 5
A22: Checkout | B22: =COUNTIF('Execution Tracker'!$B$2:$B$68,A22) -> 4 | C22: =COUNTIFS('Execution Tracker'!$B$2:$B$68,$A22,'Execution Tracker'!$D$2:$D$68,"Pass") -> 0 | D22: =COUNTIFS('Execution Tracker'!$B$2:$B$68,$A22,'Execution Tracker'!$D$2:$D$68,"Fail") -> 0 | E22: =COUNTIFS('Execution Tracker'!$B$2:$B$68,$A22,'Execution Tracker'!$D$2:$D$68,"Blocked") -> 0 | F22: =COUNTIFS('Execution Tracker'!$B$2:$B$68,$A22,'Execution Tracker'!$D$2:$D$68,"Not Executed") -> 4
A23: Address Validation | B23: =COUNTIF('Execution Tracker'!$B$2:$B$68,A23) -> 5 | C23: =COUNTIFS('Execution Tracker'!$B$2:$B$68,$A23,'Execution Tracker'!$D$2:$D$68,"Pass") -> 0 | D23: =COUNTIFS('Execution Tracker'!$B$2:$B$68,$A23,'Execution Tracker'!$D$2:$D$68,"Fail") -> 0 | E23: =COUNTIFS('Execution Tracker'!$B$2:$B$68,$A23,'Execution Tracker'!$D$2:$D$68,"Blocked") -> 0 | F23: =COUNTIFS('Execution Tracker'!$B$2:$B$68,$A23,'Execution Tracker'!$D$2:$D$68,"Not Executed") -> 5
A24: Order Placement | B24: =COUNTIF('Execution Tracker'!$B$2:$B$68,A24) -> 4 | C24: =COUNTIFS('Execution Tracker'!$B$2:$B$68,$A24,'Execution Tracker'!$D$2:$D$68,"Pass") -> 0 | D24: =COUNTIFS('Execution Tracker'!$B$2:$B$68,$A24,'Execution Tracker'!$D$2:$D$68,"Fail") -> 0 | E24: =COUNTIFS('Execution Tracker'!$B$2:$B$68,$A24,'Execution Tracker'!$D$2:$D$68,"Blocked") -> 0 | F24: =COUNTIFS('Execution Tracker'!$B$2:$B$68,$A24,'Execution Tracker'!$D$2:$D$68,"Not Executed") -> 4
A25: Payment Status Simulation | B25: =COUNTIF('Execution Tracker'!$B$2:$B$68,A25) -> 5 | C25: =COUNTIFS('Execution Tracker'!$B$2:$B$68,$A25,'Execution Tracker'!$D$2:$D$68,"Pass") -> 0 | D25: =COUNTIFS('Execution Tracker'!$B$2:$B$68,$A25,'Execution Tracker'!$D$2:$D$68,"Fail") -> 0 | E25: =COUNTIFS('Execution Tracker'!$B$2:$B$68,$A25,'Execution Tracker'!$D$2:$D$68,"Blocked") -> 0 | F25: =COUNTIFS('Execution Tracker'!$B$2:$B$68,$A25,'Execution Tracker'!$D$2:$D$68,"Not Executed") -> 5
A26: Order History | B26: =COUNTIF('Execution Tracker'!$B$2:$B$68,A26) -> 3 | C26: =COUNTIFS('Execution Tracker'!$B$2:$B$68,$A26,'Execution Tracker'!$D$2:$D$68,"Pass") -> 0 | D26: =COUNTIFS('Execution Tracker'!$B$2:$B$68,$A26,'Execution Tracker'!$D$2:$D$68,"Fail") -> 0 | E26: =COUNTIFS('Execution Tracker'!$B$2:$B$68,$A26,'Execution Tracker'!$D$2:$D$68,"Blocked") -> 0 | F26: =COUNTIFS('Execution Tracker'!$B$2:$B$68,$A26,'Execution Tracker'!$D$2:$D$68,"Not Executed") -> 3
A27: Order Cancellation | B27: =COUNTIF('Execution Tracker'!$B$2:$B$68,A27) -> 5 | C27: =COUNTIFS('Execution Tracker'!$B$2:$B$68,$A27,'Execution Tracker'!$D$2:$D$68,"Pass") -> 0 | D27: =COUNTIFS('Execution Tracker'!$B$2:$B$68,$A27,'Execution Tracker'!$D$2:$D$68,"Fail") -> 0 | E27: =COUNTIFS('Execution Tracker'!$B$2:$B$68,$A27,'Execution Tracker'!$D$2:$D$68,"Blocked") -> 0 | F27: =COUNTIFS('Execution Tracker'!$B$2:$B$68,$A27,'Execution Tracker'!$D$2:$D$68,"Not Executed") -> 5
... A29: End-to-End | B29: =COUNTIF('Execution Tracker'!$B$2:$B$68,A29) -> 3 | C29: =COUNTIFS('Execution Tracker'!$B$2:$B$68,$A29,'Execution Tracker'!$D$2:$D$68,"Pass") -> 0 | D29: =COUNTIFS('Execution Tracker'!$B$2:$B$68,$A29,'Execution Tracker'!$D$2:$D$68,"Fail") -> 0 | E29: =COUNTIFS('Execution Tracker'!$B$2:$B$68,$A29,'Execution Tracker'!$D$2:$D$68,"Blocked") -> 0 | F29: =COUNTIFS('Execution Tracker'!$B$2:$B$68,$A29,'Execution Tracker'!$D$2:$D$68,"Not Executed") -> 3
A31: Results by priority
A32: Priority | B32: Total | C32: Pass | D32: Fail | E32: Blocked | F32: Not Executed
A33: High | B33: =COUNTIF('Execution Tracker'!$C$2:$C$68,A33) -> 49 | C33: =COUNTIFS('Execution Tracker'!$C$2:$C$68,$A33,'Execution Tracker'!$D$2:$D$68,"Pass") -> 0 | D33: =COUNTIFS('Execution Tracker'!$C$2:$C$68,$A33,'Execution Tracker'!$D$2:$D$68,"Fail") -> 0 | E33: =COUNTIFS('Execution Tracker'!$C$2:$C$68,$A33,'Execution Tracker'!$D$2:$D$68,"Blocked") -> 0 | F33: =COUNTIFS('Execution Tracker'!$C$2:$C$68,$A33,'Execution Tracker'!$D$2:$D$68,"Not Executed") -> 49
A34: Medium | B34: =COUNTIF('Execution Tracker'!$C$2:$C$68,A34) -> 17 | C34: =COUNTIFS('Execution Tracker'!$C$2:$C$68,$A34,'Execution Tracker'!$D$2:$D$68,"Pass") -> 0 | D34: =COUNTIFS('Execution Tracker'!$C$2:$C$68,$A34,'Execution Tracker'!$D$2:$D$68,"Fail") -> 0 | E34: =COUNTIFS('Execution Tracker'!$C$2:$C$68,$A34,'Execution Tracker'!$D$2:$D$68,"Blocked") -> 0 | F34: =COUNTIFS('Execution Tracker'!$C$2:$C$68,$A34,'Execution Tracker'!$D$2:$D$68,"Not Executed") -> 17
A35: Low | B35: =COUNTIF('Execution Tracker'!$C$2:$C$68,A35) -> 1 | C35: =COUNTIFS('Execution Tracker'!$C$2:$C$68,$A35,'Execution Tracker'!$D$2:$D$68,"Pass") -> 0 | D35: =COUNTIFS('Execution Tracker'!$C$2:$C$68,$A35,'Execution Tracker'!$D$2:$D$68,"Fail") -> 0 | E35: =COUNTIFS('Execution Tracker'!$C$2:$C$68,$A35,'Execution Tracker'!$D$2:$D$68,"Blocked") -> 0 | F35: =COUNTIFS('Execution Tracker'!$C$2:$C$68,$A35,'Execution Tracker'!$D$2:$D$68,"Not Executed") -> 1
A37: Actual defects (Type = ACTUAL only; samples excluded)
A38: Severity | B38: Total | C38: Open (not Closed, Rejected or Duplicate)
A39: Critical | B39: =COUNTIFS('Defect Tracker'!$B$2:$B$41,"ACTUAL",'Defect Tracker'!$J$2:$J$41,A39) -> 0 | C39: =B39-COUNTIFS('Defect Tracker'!$B$2:$B$41,"ACTUAL",'Defect Tracker'!$J$2:$J$41,A39,'Defect Tracker'!$M$2:$M$41,"Closed")-COUNTIFS('Defect Tracker'!$B$2:$B$41,"ACTUAL",'Defect Tracker'!$J$2:$J$41,A39,'Defect Tracker'!$M$2:$M$41,"Rejected")-COUNTIFS('Defect Tracker'!$B$2:$B$41,"ACTUAL",'Defect Tracker'!$J$2:$J$41,A39,'Defect Tracker'!$M$2:$M$41,"Duplicate") -> 0
A40: High | B40: =COUNTIFS('Defect Tracker'!$B$2:$B$41,"ACTUAL",'Defect Tracker'!$J$2:$J$41,A40) -> 0 | C40: =B40-COUNTIFS('Defect Tracker'!$B$2:$B$41,"ACTUAL",'Defect Tracker'!$J$2:$J$41,A40,'Defect Tracker'!$M$2:$M$41,"Closed")-COUNTIFS('Defect Tracker'!$B$2:$B$41,"ACTUAL",'Defect Tracker'!$J$2:$J$41,A40,'Defect Tracker'!$M$2:$M$41,"Rejected")-COUNTIFS('Defect Tracker'!$B$2:$B$41,"ACTUAL",'Defect Tracker'!$J$2:$J$41,A40,'Defect Tracker'!$M$2:$M$41,"Duplicate") -> 0
A41: Medium | B41: =COUNTIFS('Defect Tracker'!$B$2:$B$41,"ACTUAL",'Defect Tracker'!$J$2:$J$41,A41) -> 0 | C41: =B41-COUNTIFS('Defect Tracker'!$B$2:$B$41,"ACTUAL",'Defect Tracker'!$J$2:$J$41,A41,'Defect Tracker'!$M$2:$M$41,"Closed")-COUNTIFS('Defect Tracker'!$B$2:$B$41,"ACTUAL",'Defect Tracker'!$J$2:$J$41,A41,'Defect Tracker'!$M$2:$M$41,"Rejected")-COUNTIFS('Defect Tracker'!$B$2:$B$41,"ACTUAL",'Defect Tracker'!$J$2:$J$41,A41,'Defect Tracker'!$M$2:$M$41,"Duplicate") -> 0
A42: Low | B42: =COUNTIFS('Defect Tracker'!$B$2:$B$41,"ACTUAL",'Defect Tracker'!$J$2:$J$41,A42) -> 0 | C42: =B42-COUNTIFS('Defect Tracker'!$B$2:$B$41,"ACTUAL",'Defect Tracker'!$J$2:$J$41,A42,'Defect Tracker'!$M$2:$M$41,"Closed")-COUNTIFS('Defect Tracker'!$B$2:$B$41,"ACTUAL",'Defect Tracker'!$J$2:$J$41,A42,'Defect Tracker'!$M$2:$M$41,"Rejected")-COUNTIFS('Defect Tracker'!$B$2:$B$41,"ACTUAL",'Defect Tracker'!$J$2:$J$41,A42,'Defect Tracker'!$M$2:$M$41,"Duplicate") -> 0

Sheet Execution Tracker
A1: TC ID | B1: Module | C1: Priority | D1: Status | E1: Executed By | F1: Execution Date | G1: Actual Result (what you saw) | H1: Defect ID | I1: Remarks
A2: TC_REG_01 | B2: User Registration | C2: High | D2: Not Executed
A3: TC_REG_02 | B3: User Registration | C3: High | D3: Not Executed
A4: TC_REG_03 | B4: User Registration | C4: Medium | D4: Not Executed
A5: TC_REG_04 | B5: User Registration | C5: High | D5: Not Executed
A6: TC_REG_05 | B6: User Registration | C6: High | D6: Not Executed
A7: TC_REG_06 | B7: User Registration | C7: High | D7: Not Executed
A8: TC_REG_07 | B8: User Registration | C8: High | D8: Not Executed
A9: TC_REG_08 | B9: User Registration | C9: Medium | D9: Not Executed
A10: TC_REG_09 | B10: User Registration | C10: High | D10: Not Executed
A11: TC_LOG_01 | B11: Login and Logout | C11: High | D11: Not Executed
A12: TC_LOG_02 | B12: Login and Logout | C12: High | D12: Not Executed
A13: TC_LOG_03 | B13: Login and Logout | C13: Medium | D13: Not Executed
... A68: TC_E2E_03 | B68: End-to-End | C68: High | D68: Not Executed

Sheet Test Cases
A1: TC ID | B1: Module | C1: Test Scenario | D1: Preconditions | E1: Test Data | F1: Test Steps | G1: Expected Result | H1: Actual Result | I1: Status | J1: Priority | K1: Test Type
A2: TC_REG_01 | B2: User Registration | C2: Register with valid details | D2: User not logged in; email and phone not registered | E2: First: Anitha, Last: Rao, Email: anitha.rao@example.com, Phone: 9123456780, Password: Pass@1234, Confirm: Pass@1234 | F2: 1. Open Register page 2. Enter the test data 3. Click Register | G2: Account created, success message shown, user redirected to Login. DB: 1 new customers row, status ACTIVE, password stored as hash (SQL Q01) | H2: =IF('Execution Tracker'!G2="","",'Execution Tracker'!G2) | I2: ='Execution Tracker'!D2 -> Not Executed | J2: High | K2: Positive
A3: TC_REG_02 | B3: User Registration | C3: Register with an already registered email | D3: ravi.kumar@example.com already exists | E3: Email: ravi.kumar@example.com, Phone: 9123456781, other fields valid | F3: 1. Open Register page 2. Enter data with the existing email 3. Click Register | G3: Error 'Email already registered'; no new customer row (SQL Q02 returns 0 rows) | H3: =IF('Execution Tracker'!G3="","",'Execution Tracker'!G3) | I3: ='Execution Tracker'!D3 -> Not Executed | J3: High | K3: Negative
A4: TC_REG_03 | B4: User Registration | C4: Register with an already registered phone number | D4: Phone 9876543210 already exists | E4: Phone: 9876543210, Email: new.user1@example.com, other fields valid | F4: 1. Open Register page 2. Enter data with the existing phone 3. Click Register | G4: Error 'Phone number already registered'; no new row (SQL Q03 returns 0 rows) | H4: =IF('Execution Tracker'!G4="","",'Execution Tracker'!G4) | I4: ='Execution Tracker'!D4 -> Not Executed | J4: Medium | K4: Negative
A5: TC_REG_04 | B5: User Registration | C5: Invalid email formats are rejected | D5: Register page open | E5: ravi.kumar@ ; ravi@.com ; ravi kumar@example.com ; ravi.example.com | F5: 1. Enter each invalid email one by one with other valid data 2. Click Register after each | G5: Each attempt shows 'Enter a valid email address'; no account created | H5: =IF('Execution Tracker'!G5="","",'Execution Tracker'!G5) | I5: ='Execution Tracker'!D5 -> Not Executed | J5: High | K5: Validation
A6: TC_REG_05 | B6: User Registration | C6: Mandatory fields left blank | D6: Register page open | E6: All fields empty | F6: 1. Click Register without entering anything | G6: Inline error shown for every mandatory field; form not submitted | H6: =IF('Execution Tracker'!G6="","",'Execution Tracker'!G6) | I6: ='Execution Tracker'!D6 -> Not Executed | J6: High | K6: Negative
A7: TC_REG_06 | B7: User Registration | C7: Weak passwords are rejected (password policy) | D7: Register page open | E7: abcd1234 (no uppercase/special) ; PASSWORD@1 (no lowercase) ; Password@ (no digit) ; Pass1234 (no special) | F7: 1. Fill valid data and enter one weak password 2. Click Register 3. Repeat for each password | G7: Each is rejected and the message lists the missing rule (BR-02) | H7: =IF('Execution Tracker'!G7="","",'Execution Tracker'!G7) | I7: ='Execution Tracker'!D7 -> Not Executed | J7: High | K7: Validation
A8: TC_REG_07 | B8: User Registration | C8: Password length boundary values | D8: Register page open | E8: 7 chars: Pass@12 ; 8 chars: Pass@123 ; 20 chars: Passw@rd123456789012 ; 21 chars: Passw@rd1234567890123 | F8: 1. Enter each password with valid other data 2. Click Register | G8: 7 and 21 characters rejected; 8 and 20 characters accepted (use a unique email each time) | H8: =IF('Execution Tracker'!G8="","",'Execution Tracker'!G8) | I8: ='Execution Tracker'!D8 -> Not Executed | J8: High | K8: Boundary
A9: TC_REG_08 | B9: User Registration | C9: Confirm password does not match | D9: Register page open | E9: Password: Pass@1234, Confirm: Pass@12345 | F9: 1. Enter mismatching passwords 2. Click Register | G9: Error 'Passwords do not match'; account not created | H9: =IF('Execution Tracker'!G9="","",'Execution Tracker'!G9) | I9: ='Execution Tracker'!D9 -> Not Executed | J9: Medium | K9: Negative
A10: TC_REG_09 | B10: User Registration | C10: Phone number validation | D10: Register page open | E10: 12345 ; 5876543210 (starts with 5) ; 98765abcde ; 98765432101 (11 digits) | F10: 1. Enter each phone value with other valid data 2. Click Register | G10: All rejected; only 10 digits starting 6-9 allowed (BR-01) | H10: =IF('Execution Tracker'!G10="","",'Execution Tracker'!G10) | I10: ='Execution Tracker'!D10 -> Not Executed | J10: High | K10: Validation
A11: TC_LOG_01 | B11: Login and Logout | C11: Login with valid credentials | D11: Registered ACTIVE user | E11: ravi.kumar@example.com / Test@1234 | F11: 1. Open Login page 2. Enter email and password 3. Click Login | G11: Login succeeds, home page shows user name. DB: last_login_at updated, failed_login_attempts = 0 | H11: =IF('Execution Tracker'!G11="","",'Execution Tracker'!G11) | I11: ='Execution Tracker'!D11 -> Not Executed | J11: High | K11: Positive
A12: TC_LOG_02 | B12: Login and Logout | C12: Login with wrong password | D12: Registered ACTIVE user | E12: ravi.kumar@example.com / Wrong@123 | F12: 1. Enter valid email and wrong password 2. Click Login | G12: Generic message 'Invalid email or password'; not logged in. DB: failed_login_attempts increased by 1 | H12: =IF('Execution Tracker'!G12="","",'Execution Tracker'!G12) | I12: ='Execution Tracker'!D12 -> Not Executed | J12: High | K12: Negative
A13: TC_LOG_03 | B13: Login and Logout | C13: Login with unregistered email | D13: None | E13: nobody@example.com / Test@1234 | F13: 1. Enter unregistered email and any password 2. Click Login | G13: Same generic message (does not reveal that the email is unknown) | H13: =IF('Execution Tracker'!G13="","",'Execution Tracker'!G13) | I13: ='Execution Tracker'!D13 -> Not Executed | J13: Medium | K13: Negative
... A68: TC_E2E_03 | B68: End-to-End | C68: Failed payment then successful retry | D68: Logged-in user with address | E68: Nova Lite x1; first card ending 0002, then UPI success@shopease | F68: 1. Place order and fail card payment 2. Verify PAYMENT_FAILED and stock unchanged 3. Retry payment using UPI 4. Verify final state in DB | G68: Single order ends CONFIRMED, payment SUCCESS with transaction id, stock reduced once, no duplicate order (SQL Q19, Q23, Q27) | H68: =IF('Execution Tracker'!G68="","",'Execution Tracker'!G68) | I68: ='Execution Tracker'!D68 -> Not Executed | J68: High | K68: End-to-End

Sheet Defect Tracker
A1: Bug ID | B1: Type | C1: Summary | D1: Module | E1: Linked TC | F1: Preconditions | G1: Steps to Reproduce | H1: Expected Result | I1: Actual Result | J1: Severity | K1: Priority | L1: Environment | M1: Status | N1: Reported By | O1: Reported Date | P1: SQL Evidence
A2: BUG-S01 | B2: SAMPLE | C2: Cart subtotal wrong after increasing quantity | D2: Quantity Updates | E2: TC_QTY_01 | F2: User logged in. Steel Water Bottle (Rs.349) in cart with quantity 1. | G2: 1. Open the cart. 2. Change quantity of Steel Water Bottle from 1 to 3. 3. Click Update. 4. Read line total and cart subtotal. | H2: Line total Rs.1,047.00 and cart subtotal Rs.1,047.00 (Q12 shows the same). | I2: Line total shows Rs.1,047.00 but cart subtotal shows Rs.698.00 (quantity counted as 2). | J2: High | K2: High | L2: Simulated ShopEase test build v0.1 (fictional), Chrome latest, Windows 11, MySQL 8.0 database shopease_db | M2: New (SAMPLE, not a real finding) | N2: Sample | O2: n/a | P2: Q12
A3: BUG-S02 | B3: SAMPLE | C3: Stock not reduced after a successful order | D3: Inventory Validation | E3: TC_INV_01 | F3: ChargePro stock noted as 200. User has valid cart and address. | G3: 1. Note quantity_available of ChargePro (200). 2. Add ChargePro x2 to cart. 3. Place order and pay with UPI success@shopease. 4. Query inventory for the product. | H3: quantity_available = 198 (reduced by 2, rule BR-16). | I3: quantity_available is still 200. Order shows CONFIRMED. Risk of selling stock that does not exist. | J3: High | K3: High | L3: Simulated ShopEase test build v0.1 (fictional), Chrome latest, Windows 11, MySQL 8.0 database shopease_db | M3: New (SAMPLE, not a real finding) | N3: Sample | O3: n/a | P3: Q34, Q32
A4: BUG-S03 | B4: SAMPLE | C4: Checkout accepts pincode starting with 0 | D4: Address Validation | E4: TC_ADR_03 | F4: User at checkout, Add Address form open. | G4: 1. Enter valid name, phone, line 1, city, state. 2. Enter pincode 017501. 3. Click Save and continue to payment. | H4: Error 'Enter a valid 6-digit pincode' and address not saved (BR-12). | I4: Address saved and checkout continues. A row with pincode 017501 is stored. | J4: Medium | K4: Medium | L4: Simulated ShopEase test build v0.1 (fictional), Chrome latest, Windows 11, MySQL 8.0 database shopease_db | M4: New (SAMPLE, not a real finding) | N4: Sample | O4: n/a | P4: Q39 (and review addresses table)
A5: BUG-S04 | B5: SAMPLE | C5: Order shows CONFIRMED after card payment failed | D5: Payment Status Simulation | E5: TC_PAY_02 | F5: Order ready for payment. Simulated card ending 0002 declines. | G5: 1. Place an order and choose Debit Card. 2. Enter the declined test card with valid expiry and CVV. 3. Click Pay. 4. Open Order History and query the order. | H5: Order status PAYMENT_FAILED, payment FAILED with a failure reason (BR-15). | I5: Payment row is FAILED but order status is CONFIRMED, so the order would be shipped without payment. | J5: Critical | K5: High | L5: Simulated ShopEase test build v0.1 (fictional), Chrome latest, Windows 11, MySQL 8.0 database shopease_db | M5: New (SAMPLE, not a real finding) | N5: Sample | O5: n/a | P5: Q27, Q28
A6: BUG-S05 | B6: SAMPLE | C6: Double click on Place Order creates two orders | D6: Order Placement | E6: TC_ORD_02 | F6: Cart ready, address selected. | G6: 1. Open checkout. 2. Double-click Place Order quickly. 3. Open Order History and query orders for the customer. | H6: Exactly one order is created. | I6: Two orders with different order numbers and the same items are created; stock reduced twice. | J6: High | K6: High | L6: Simulated ShopEase test build v0.1 (fictional), Chrome latest, Windows 11, MySQL 8.0 database shopease_db | M6: New (SAMPLE, not a real finding) | N6: Sample | O6: n/a | P6: Q46, Q30, Q34
A7: BUG-S06 | B7: SAMPLE | C7: Cash on Delivery offered for order above Rs.10,000 | D7: Payment Status Simulation | E7: TC_PAY_04 | F7: Cart contains Nova Lite Smartphone (total Rs.10,618.82). | G7: 1. Open checkout with the cart. 2. Go to payment step. 3. Select Cash on Delivery and place the order. | H7: COD option disabled with a message (BR-13). | I7: COD is selectable and the order is placed with total 10,618.82. | J7: High | K7: Medium | L7: Simulated ShopEase test build v0.1 (fictional), Chrome latest, Windows 11, MySQL 8.0 database shopease_db | M7: New (SAMPLE, not a real finding) | N7: Sample | O7: n/a | P7: Q29
A8: BUG-S07 | B8: SAMPLE | C8: Account not blocked after 5 wrong passwords | D8: Login and Logout | E8: TC_LOG_05 | F8: User priya.nair@example.com ACTIVE with 0 failed attempts. | G8: 1. Enter a wrong password 5 times. 2. Enter the correct password Test@1234. | H8: Account status BLOCKED after the 5th failure; correct password rejected (BR-04). | I8: Status stays ACTIVE with failed_login_attempts 6; login with the correct password succeeds. | J8: High | K8: High | L8: Simulated ShopEase test build v0.1 (fictional), Chrome latest, Windows 11, MySQL 8.0 database shopease_db | M8: New (SAMPLE, not a real finding) | N8: Sample | O8: n/a | P8: Q06
A9: BUG-S08 | B9: SAMPLE | C9: Cancelled prepaid order is not refunded | D9: Order Cancellation | E9: TC_CAN_02 | F9: UPI order in CONFIRMED state. | G9: 1. Open the order in My Orders. 2. Click Cancel Order and choose a reason. 3. Query orders and payments for the order. | H9: Order CANCELLED, payment REFUNDED (BR-17). | I9: Order CANCELLED but payment still SUCCESS; no refund recorded. | J9: Critical | K9: High | L9: Simulated ShopEase test build v0.1 (fictional), Chrome latest, Windows 11, MySQL 8.0 database shopease_db | M9: New (SAMPLE, not a real finding) | N9: Sample | O9: n/a | P9: Q25, Q40
A10: BUG-S09 | B10: SAMPLE | C10: Shipping fee charged when subtotal is exactly Rs.500 | D10: Checkout | E10: TC_CHK_03 | F10: Notebook Pack (Rs.250) available. | G10: 1. Add 2 Notebook Packs (subtotal Rs.500). 2. Open checkout and read shipping fee. | H10: Shipping Rs.0, GST 90.00, total 590.00 (BR-10: free from Rs.500). | I10: Shipping Rs.40.00 and total 630.00 (rule applied as 'above 500'). | J10: Medium | K10: Medium | L10: Simulated ShopEase test build v0.1 (fictional), Chrome latest, Windows 11, MySQL 8.0 database shopease_db | M10: New (SAMPLE, not a real finding) | N10: Sample | O10: n/a | P10: Q18, Q16
A11: BUG-S10 | B11: SAMPLE | C11: Brand name misspelled in site header | D11: Product Search | E11: TC_SRC_01 | F11: Home page open. | G11: 1. Open the home page. 2. Read the header text. | H11: Header shows 'ShopEase'. | I11: Header shows 'ShopEse'. | J11: Low | K11: High | L11: Simulated ShopEase test build v0.1 (fictional), Chrome latest, Windows 11, MySQL 8.0 database shopease_db | M11: New (SAMPLE, not a real finding) | N11: Sample | O11: n/a | P11: None (UI text only)
B12: ACTUAL
B13: ACTUAL
B14: ACTUAL
B15: ACTUAL
B16: ACTUAL
B17: ACTUAL
B18: ACTUAL
B19: ACTUAL
B20: ACTUAL
B21: ACTUAL
B22: ACTUAL
B23: ACTUAL
... B41: ACTUAL

Sheet RTM
A1: Requirement ID | B1: Test Case ID | C1: Manual Test | D1: Related Database Table | E1: SQL Validation Query ID | F1: Expected Database State | G1: Execution Status
A2: FR-01 (BR-01, BR-02, BR-03) | B2: TC_REG_01 | C2: Register with valid details | D2: customers | E2: Q01, Q02, Q03, Q44 | F2: 1 new customers row; status ACTIVE; failed_login_attempts 0; password_hash is not plain text | G2: =INDEX('Execution Tracker'!$D$2:$D$68,MATCH(B2,'Execution Tracker'!$A$2:$A$68,0)) -> Not Executed
A3: FR-01 (BR-01) | B3: TC_REG_02 | C3: Register with an already registered email | D3: customers | E3: Q02 | F3: Row count unchanged; no duplicate email | G3: =INDEX('Execution Tracker'!$D$2:$D$68,MATCH(B3,'Execution Tracker'!$A$2:$A$68,0)) -> Not Executed
A4: FR-01 (BR-01) | B4: TC_REG_03 | C4: Register with an already registered phone number | D4: customers | E4: Q03 | F4: Row count unchanged; no duplicate phone | G4: =INDEX('Execution Tracker'!$D$2:$D$68,MATCH(B4,'Execution Tracker'!$A$2:$A$68,0)) -> Not Executed
A5: FR-01 (BR-01) | B5: TC_REG_04 | C5: Invalid email formats are rejected | D5: customers | E5: Q04 | F5: No new row; no invalid email stored | G5: =INDEX('Execution Tracker'!$D$2:$D$68,MATCH(B5,'Execution Tracker'!$A$2:$A$68,0)) -> Not Executed
A6: FR-01 | B6: TC_REG_05 | C6: Mandatory fields left blank | D6: customers | E6: Q39, Q44 | F6: No new row; no blank mandatory value stored | G6: =INDEX('Execution Tracker'!$D$2:$D$68,MATCH(B6,'Execution Tracker'!$A$2:$A$68,0)) -> Not Executed
A7: FR-01 (BR-02) | B7: TC_REG_06 | C7: Weak passwords are rejected (password policy) | D7: customers | E7: Q44 | F7: No new row for each weak password | G7: =INDEX('Execution Tracker'!$D$2:$D$68,MATCH(B7,'Execution Tracker'!$A$2:$A$68,0)) -> Not Executed
A8: FR-01 (BR-02) | B8: TC_REG_07 | C8: Password length boundary values | D8: customers | E8: Q44 | F8: New rows only for 8 and 20 character passwords; none for 7 and 21 | G8: =INDEX('Execution Tracker'!$D$2:$D$68,MATCH(B8,'Execution Tracker'!$A$2:$A$68,0)) -> Not Executed
A9: FR-01 (BR-02) | B9: TC_REG_08 | C9: Confirm password does not match | D9: customers | E9: Q44 | F9: No new row | G9: =INDEX('Execution Tracker'!$D$2:$D$68,MATCH(B9,'Execution Tracker'!$A$2:$A$68,0)) -> Not Executed
A10: FR-01 (BR-01) | B10: TC_REG_09 | C10: Phone number validation | D10: customers | E10: Q39, Q44 | F10: No new row; stored phones are all 10 digits starting 6-9 | G10: =INDEX('Execution Tracker'!$D$2:$D$68,MATCH(B10,'Execution Tracker'!$A$2:$A$68,0)) -> Not Executed
A11: FR-02 | B11: TC_LOG_01 | C11: Login with valid credentials | D11: customers | E11: Q06 | F11: last_login_at updated; failed_login_attempts = 0 | G11: =INDEX('Execution Tracker'!$D$2:$D$68,MATCH(B11,'Execution Tracker'!$A$2:$A$68,0)) -> Not Executed
A12: FR-02 (BR-04) | B12: TC_LOG_02 | C12: Login with wrong password | D12: customers | E12: Q06 | F12: failed_login_attempts increased by 1; status still ACTIVE | G12: =INDEX('Execution Tracker'!$D$2:$D$68,MATCH(B12,'Execution Tracker'!$A$2:$A$68,0)) -> Not Executed
A13: FR-02 | B13: TC_LOG_03 | C13: Login with unregistered email | D13: customers | E13: Q44 | F13: No change in any table | G13: =INDEX('Execution Tracker'!$D$2:$D$68,MATCH(B13,'Execution Tracker'!$A$2:$A$68,0)) -> Not Executed
... A68: FR-09, FR-10, FR-13 | B68: TC_E2E_03 | C68: Failed payment then successful retry | D68: orders, payments, inventory | E68: Q19, Q23, Q27, Q28, Q34 | F68: One order ends CONFIRMED; one payment SUCCESS; stock reduced once | G68: =INDEX('Execution Tracker'!$D$2:$D$68,MATCH(B68,'Execution Tracker'!$A$2:$A$68,0)) -> Not Executed
